{
  "Id": "NpcAbilitiesHigh",
  "npcAbilitiesHigh": [
    {
      "ability": "Strength-powerful, brawny, strong as an ox",
      "id": 1
    },
    {
      "ability": "Dexterity-lithe, agile, graceful",
      "id": 2
    },
    {
      "ability": "Constitution-hardy, hale, healthy",
      "id": 3
    },
    {
      "ability": "Intelligence-studious, learned, inquisitive",
      "id": 4
    },
    {
      "ability": "Wisdom-perceptive, spiritual, insightful",
      "id": 5
    },
    {
      "ability": "Charisma-persuasive, forceful, born leader",
      "id": 6
    }
  ]
}